links_to_hugo_post/__init__.py
links_to_hugo_post/console.py
links_to_hugo_post/py.typed
links_to_hugo_post/workflow.py
links_to_hugo_post-0.4.0.dist-info/entry_points.txt
links_to_hugo_post-0.4.0.dist-info/WHEEL
links_to_hugo_post-0.4.0.dist-info/METADATA
links_to_hugo_post-0.4.0.dist-info/RECORD
