Metadata-Version: 2.1
Name: links-to-hugo-post
Version: 0.4.0
Summary: Convert a list of links to a Hugo blog post
Home-page: https://namuan.github.io/links-to-hugo-post
License: MIT
Author: namuan
Author-email: github@deskriders.dev
Requires-Python: >=3.7.1,<4.0
Classifier: Development Status :: 4 - Beta
Classifier: Intended Audience :: Developers
Classifier: License :: OSI Approved :: MIT License
Classifier: Operating System :: OS Independent
Classifier: Programming Language :: Python
Classifier: Programming Language :: Python :: 3
Classifier: Programming Language :: Python :: 3.10
Classifier: Programming Language :: Python :: 3.7
Classifier: Programming Language :: Python :: 3.8
Classifier: Programming Language :: Python :: 3.9
Classifier: Topic :: Software Development :: Libraries :: Python Modules
Classifier: Typing :: Typed
Requires-Dist: py-executable-checklist (>=0.9.0,<0.10.0)
Requires-Dist: slug (>=2.0,<3.0)
Project-URL: Documentation, https://namuan.github.io/links-to-hugo-post
Project-URL: Repository, https://github.com/namuan/links-to-hugo-post
